foundpy/__init__.py
foundpy/cast.py
foundpy/config.py
foundpy/contract.py
foundpy/forge.py
foundpy/util.py
foundpy-0.3.0.dist-info/METADATA
foundpy-0.3.0.dist-info/WHEEL
foundpy-0.3.0.dist-info/licenses/LICENSE
foundpy-0.3.0.dist-info/RECORD
