Metadata-Version: 2.4
Name: foundpy
Version: 0.3.0
Summary: Python implementation of Foundry using python web3 module 
Project-URL: Homepage, https://github.com/Wrth1/foundpy
Project-URL: Repository, https://github.com/Wrth1/foundpy.git
Project-URL: Issues, https://github.com/Wrth1/foundpy/issues
Author-email: Bill Elim <billelimgg@gmail.com>
License-File: LICENSE
Classifier: License :: OSI Approved :: MIT License
Classifier: Operating System :: OS Independent
Classifier: Programming Language :: Python :: 3
Requires-Python: >=3.8
Requires-Dist: eth-abi>=5.1.0
Requires-Dist: hexbytes>=1.2.1
Requires-Dist: py-solc-x>=2.0.3
Requires-Dist: requests>=2.32.3
Requires-Dist: tqdm>=4.66.5
Requires-Dist: web3>=7.4.0
